MANIFEST.in
setup.py
reactopya_examples_jup/__init__.py
reactopya_examples_jup/_version.py
reactopya_examples_jup/all_widgets.py
reactopya_examples_jup/init.py
reactopya_examples_jup.egg-info/PKG-INFO
reactopya_examples_jup.egg-info/SOURCES.txt
reactopya_examples_jup.egg-info/dependency_links.txt
reactopya_examples_jup.egg-info/requires.txt
reactopya_examples_jup.egg-info/top_level.txt
reactopya_examples_jup/dist/bundle.js
reactopya_examples_jup/widgets/__init__.py
reactopya_examples_jup/widgets/create_sync.py
reactopya_examples_jup/widgets/jupyter.py
reactopya_examples_jup/widgets/Accordion/Accordion.py
reactopya_examples_jup/widgets/Accordion/__init__.py
reactopya_examples_jup/widgets/HBox/HBox.py
reactopya_examples_jup/widgets/HBox/__init__.py
reactopya_examples_jup/widgets/InteractivePlotly/InteractivePlotly.py
reactopya_examples_jup/widgets/InteractivePlotly/__init__.py
reactopya_examples_jup/widgets/PlotlyExample/PlotlyExample.py
reactopya_examples_jup/widgets/PlotlyExample/__init__.py
reactopya_examples_jup/widgets/Tabs/Tabs.py
reactopya_examples_jup/widgets/Tabs/__init__.py
reactopya_examples_jup/widgets/VBox/VBox.py
reactopya_examples_jup/widgets/VBox/__init__.py